flask_inertia/__init__.py
flask_inertia/inertia.py
flask_inertia/props.py
flask_inertia/router.js
flask_inertia/unittest.py
flask_inertia/version.py
flask_inertia/views.py
flask_inertia_blueprint-0.1.1.dist-info/LICENSE
flask_inertia_blueprint-0.1.1.dist-info/METADATA
flask_inertia_blueprint-0.1.1.dist-info/WHEEL
flask_inertia_blueprint-0.1.1.dist-info/top_level.txt
flask_inertia_blueprint-0.1.1.dist-info/RECORD
